Workbook

Sheet Assumptions
A1: FounderFloor — Financial Model
A2: Blue cells = inputs you can edit. Yellow = the levers that matter most. Everything else recalculates.
A4: PRICING (chosen from market research)
A5: Pro — monthly | B5: 9 | C5: In-market: Gather Town tier $7/user/mo; CoFoundersLab premium $29.99/mo. Source: gather.town/pricing; coffeespace.com blog, 2026.
A6: Pro — annual (per year) | B6: 79 | C6: About 2.4 months free vs monthly. Annual smooths churn and cash.
A7: Founder+ — monthly | B7: 19 | C7: Just above Gather City tier ($15); well under CoFoundersLab ($29.99).
A8: Founder+ — annual (per year) | B8: 159 | C8: About 3.6 months free vs monthly.
A9: Founding Member (one-time, first 100) | B9: 79 | C9: Beta launch offer: a year of Founder+, price locked, permanent badge.
A10: Founding Member units sold (launch) | B10: 60 | C10: Assumption: 60 of the 100 sell across the first two months. User-set.
A12: CONVERSION & MIX
A13: Free → paid conversion | B13: 0.03 | C13: Freemium norm 2–5%; 8% is median of top products. Planned conservatively. Source: First Page Sage, SaaS Freemium Conversion Rates 2026; Guru Startups benchmarks.
A14: Payers choosing Pro (vs Founder+) | B14: 0.75 | C14: Cheaper tier dominates in freemium consumer products. User assumption.
A15: Payers choosing annual billing | B15: 0.4 | C15: User assumption; annual is pushed in the UI.
A16: Monthly churn (monthly-billed payers) | B16: 0.06 | C16: Consumer SaaS norm 5–8%/mo. Annual payers churn at renewal instead.
A18: COSTS
A19: Domain (per month, $12/yr) | B19: 1 | C19: Namecheap/porkbun .com ballpark.
A20: VPS for floor server (per month) | B20: 6 | C20: Hetzner/DO small instance runs the ws server comfortably to ~1k concurrent.
A21: Stripe fee — % of revenue | B21: 0.029 | C21: Standard Stripe pricing 2.9% + 30¢ per transaction.
A22: Stripe fee — per transaction | B22: 0.3
A24: Infrastructure steps by monthly active users (edit thresholds/costs)
A25: MAU from | B25: Infra $/mo
A26: 0 | B26: 12 | C26: Web host hobby tier free + VPS + domain + backups
A27: 1000 | B27: 52 | C27: Vercel Pro $20 + email service $20 + domain/VPS
A28: 5000 | B28: 130 | C28: Bigger VPS $40 + Vercel Pro + email at volume + monitoring
A30: DERIVED (formulas — do not edit)
A31: Blended revenue per payer per month | B31: =$B$14*($B$15*$B$6/12+(1-$B$15)*$B$5)+(1-$B$14)*($B$15*$B$8/12+(1-$B$15)*$B$7) | C31: Pro/Founder+ mix x annual/monthly mix.
A32: Transactions per payer per month | B32: =(1-$B$15)+$B$15/12 | C32: Monthly payers: 1 charge/mo; annual payers: 1 charge/yr.

Sheet P&L by scale
A1: Monthly P&L at audience milestones
A2: All figures are per month at steady state. MAU row is an input (blue).
A4: Monthly active users | B4: 100 | C4: 250 | D4: 500 | E4: 1000 | F4: 2500 | G4: 5000 | H4: 10000
A5: Paying members | B5: =ROUND(B4*Assumptions!$B$13,0) | C5: =ROUND(C4*Assumptions!$B$13,0) | D5: =ROUND(D4*Assumptions!$B$13,0) | E5: =ROUND(E4*Assumptions!$B$13,0) | F5: =ROUND(F4*Assumptions!$B$13,0) | G5: =ROUND(G4*Assumptions!$B$13,0) | H5: =ROUND(H4*Assumptions!$B$13,0)
A6: Gross subscription revenue | B6: =B5*Assumptions!$B$31 | C6: =C5*Assumptions!$B$31 | D6: =D5*Assumptions!$B$31 | E6: =E5*Assumptions!$B$31 | F6: =F5*Assumptions!$B$31 | G6: =G5*Assumptions!$B$31 | H6: =H5*Assumptions!$B$31
A7: Stripe fees | B7: =-(B6*Assumptions!$B$21+B5*Assumptions!$B$32*Assumptions!$B$22) | C7: =-(C6*Assumptions!$B$21+C5*Assumptions!$B$32*Assumptions!$B$22) | D7: =-(D6*Assumptions!$B$21+D5*Assumptions!$B$32*Assumptions!$B$22) | E7: =-(E6*Assumptions!$B$21+E5*Assumptions!$B$32*Assumptions!$B$22) | F7: =-(F6*Assumptions!$B$21+F5*Assumptions!$B$32*Assumptions!$B$22) | G7: =-(G6*Assumptions!$B$21+G5*Assumptions!$B$32*Assumptions!$B$22) | H7: =-(H6*Assumptions!$B$21+H5*Assumptions!$B$32*Assumptions!$B$22)
A8: Net revenue | B8: =B6+B7 | C8: =C6+C7 | D8: =D6+D7 | E8: =E6+E7 | F8: =F6+F7 | G8: =G6+G7 | H8: =H6+H7
A9: Infrastructure | B9: =-INDEX(Assumptions!$B$26:$B$28,MATCH(B4,Assumptions!$A$26:$A$28,1)) | C9: =-INDEX(Assumptions!$B$26:$B$28,MATCH(C4,Assumptions!$A$26:$A$28,1)) | D9: =-INDEX(Assumptions!$B$26:$B$28,MATCH(D4,Assumptions!$A$26:$A$28,1)) | E9: =-INDEX(Assumptions!$B$26:$B$28,MATCH(E4,Assumptions!$A$26:$A$28,1)) | F9: =-INDEX(Assumptions!$B$26:$B$28,MATCH(F4,Assumptions!$A$26:$A$28,1)) | G9: =-INDEX(Assumptions!$B$26:$B$28,MATCH(G4,Assumptions!$A$26:$A$28,1)) | H9: =-INDEX(Assumptions!$B$26:$B$28,MATCH(H4,Assumptions!$A$26:$A$28,1))
A10: Profit / month | B10: =B8+B9 | C10: =C8+C9 | D10: =D8+D9 | E10: =E8+E9 | F10: =F8+F9 | G10: =G8+G9 | H10: =H8+H9
A11: Margin | B11: =IF(B6=0,0,B10/B6) | C11: =IF(C6=0,0,C10/C6) | D11: =IF(D6=0,0,D10/D6) | E11: =IF(E6=0,0,E10/E6) | F11: =IF(F6=0,0,F10/F6) | G11: =IF(G6=0,0,G10/G6) | H11: =IF(H6=0,0,H10/H6)
A13: Break-even
A14: Payers needed to cover base infra | B14: =ROUNDUP(Assumptions!$B$26/ (Assumptions!$B$31*(1-Assumptions!$B$21)-Assumptions!$B$32*Assumptions!$B$22),0)
A15: MAU needed at planned conversion | B15: =ROUNDUP(B14/Assumptions!$B$13,0) | C15: ← the whole game: pass this many actives and the lights stay on.

Sheet Year 1 plan
A1: Year 1 monthly plan
A2: MAU curve is an input (blue) — a beta wave then steady word-of-mouth. Founding Member sales land in months 1–2.
A4: Month | B4: M1 | C4: M2 | D4: M3 | E4: M4 | F4: M5 | G4: M6 | H4: M7 | I4: M8 | J4: M9 | K4: M10 | L4: M11 | M4: M12
A5: Monthly active users | B5: 60 | C5: 120 | D5: 200 | E5: 300 | F5: 420 | G5: 560 | H5: 720 | I5: 900 | J5: 1100 | K5: 1350 | L5: 1650 | M5: 2000
A6: Founding Member sales (units) | B6: 40 | C6: 20 | D6: 0 | E6: 0 | F6: 0 | G6: 0 | H6: 0 | I6: 0 | J6: 0 | K6: 0 | L6: 0 | M6: 0
A7: Founding Member revenue | B7: =B6*Assumptions!$B$9 | C7: =C6*Assumptions!$B$9 | D7: =D6*Assumptions!$B$9 | E7: =E6*Assumptions!$B$9 | F7: =F6*Assumptions!$B$9 | G7: =G6*Assumptions!$B$9 | H7: =H6*Assumptions!$B$9 | I7: =I6*Assumptions!$B$9 | ... M7: =M6*Assumptions!$B$9
A8: Paying members | B8: =ROUND(B5*Assumptions!$B$13,0) | C8: =ROUND(C5*Assumptions!$B$13,0) | D8: =ROUND(D5*Assumptions!$B$13,0) | E8: =ROUND(E5*Assumptions!$B$13,0) | F8: =ROUND(F5*Assumptions!$B$13,0) | G8: =ROUND(G5*Assumptions!$B$13,0) | H8: =ROUND(H5*Assumptions!$B$13,0) | I8: =ROUND(I5*Assumptions!$B$13,0) | ... M8: =ROUND(M5*Assumptions!$B$13,0)
A9: Subscription revenue | B9: =B8*Assumptions!$B$31 | C9: =C8*Assumptions!$B$31 | D9: =D8*Assumptions!$B$31 | E9: =E8*Assumptions!$B$31 | F9: =F8*Assumptions!$B$31 | G9: =G8*Assumptions!$B$31 | H9: =H8*Assumptions!$B$31 | I9: =I8*Assumptions!$B$31 | ... M9: =M8*Assumptions!$B$31
A10: Stripe fees | B10: =-((B7+B9)*Assumptions!$B$21+(B8*Assumptions!$B$32+B6)*Assumptions!$B$22) | C10: =-((C7+C9)*Assumptions!$B$21+(C8*Assumptions!$B$32+C6)*Assumptions!$B$22) | D10: =-((D7+D9)*Assumptions!$B$21+(D8*Assumptions!$B$32+D6)*Assumptions!$B$22) | E10: =-((E7+E9)*Assumptions!$B$21+(E8*Assumptions!$B$32+E6)*Assumptions!$B$22) | F10: =-((F7+F9)*Assumptions!$B$21+(F8*Assumptions!$B$32+F6)*Assumptions!$B$22) | G10: =-((G7+G9)*Assumptions!$B$21+(G8*Assumptions!$B$32+G6)*Assumptions!$B$22) | H10: =-((H7+H9)*Assumptions!$B$21+(H8*Assumptions!$B$32+H6)*Assumptions!$B$22) | I10: =-((I7+I9)*Assumptions!$B$21+(I8*Assumptions!$B$32+I6)*Assumptions!$B$22) | ... M10: =-((M7+M9)*Assumptions!$B$21+(M8*Assumptions!$B$32+M6)*Assumptions!$B$22)
A11: Infrastructure | B11: =-INDEX(Assumptions!$B$26:$B$28,MATCH(B5,Assumptions!$A$26:$A$28,1)) | C11: =-INDEX(Assumptions!$B$26:$B$28,MATCH(C5,Assumptions!$A$26:$A$28,1)) | D11: =-INDEX(Assumptions!$B$26:$B$28,MATCH(D5,Assumptions!$A$26:$A$28,1)) | E11: =-INDEX(Assumptions!$B$26:$B$28,MATCH(E5,Assumptions!$A$26:$A$28,1)) | F11: =-INDEX(Assumptions!$B$26:$B$28,MATCH(F5,Assumptions!$A$26:$A$28,1)) | G11: =-INDEX(Assumptions!$B$26:$B$28,MATCH(G5,Assumptions!$A$26:$A$28,1)) | H11: =-INDEX(Assumptions!$B$26:$B$28,MATCH(H5,Assumptions!$A$26:$A$28,1)) | I11: =-INDEX(Assumptions!$B$26:$B$28,MATCH(I5,Assumptions!$A$26:$A$28,1)) | ... M11: =-INDEX(Assumptions!$B$26:$B$28,MATCH(M5,Assumptions!$A$26:$A$28,1))
A12: Profit / month | B12: =B7+B9+B10+B11 | C12: =C7+C9+C10+C11 | D12: =D7+D9+D10+D11 | E12: =E7+E9+E10+E11 | F12: =F7+F9+F10+F11 | G12: =G7+G9+G10+G11 | H12: =H7+H9+H10+H11 | I12: =I7+I9+I10+I11 | ... M12: =M7+M9+M10+M11
A13: Cumulative cash | B13: =B12 | C13: =B13+C12 | D13: =C13+D12 | E13: =D13+E12 | F13: =E13+F12 | G13: =F13+G12 | H13: =G13+H12 | I13: =H13+I12 | J13: =I13+J12 | ... M13: =L13+M12
A15: Notes
A16: • Every month is profitable because fixed costs are tiny ($12/mo base) — the risk is audience, not burn.
A17: • Founding Member sales are one-time cash to cover a year of infra up front and seed the community.
A18: • Churn is inside the flat conversion rate here (payers = MAU x rate at each month's size).
A19: • MAU curve is a target, not a forecast — edit the blue row to your reality each month.
